akey/__init__.py
akey/_modidx.py
akey/dims.py
akey/keys.py
akey/mock.py
akey-0.0.5.dist-info/LICENSE
akey-0.0.5.dist-info/METADATA
akey-0.0.5.dist-info/WHEEL
akey-0.0.5.dist-info/entry_points.txt
akey-0.0.5.dist-info/top_level.txt
akey-0.0.5.dist-info/RECORD
