Metadata-Version: 2.1
Name: akey
Version: 0.0.5
Summary: akey
Home-page: https://github.com/dsm-72/akey
Author: dsm-72
Author-email: sumner.magruder@yale.edu
License: Apache Software License 2.0
Keywords: akey extra extras single cell sc scanpy anndata RNA-seq seq
Classifier: Development Status :: 4 - Beta
Classifier: Intended Audience :: Developers
Classifier: Natural Language :: English
Classifier: Programming Language :: Python :: 3.11
Classifier: License :: OSI Approved :: Apache Software License
Requires-Python: >=3.11
License-File: LICENSE
Requires-Dist: atup
Requires-Dist: nchr
Requires-Dist: nlit
Requires-Dist: chck
Requires-Dist: asto
Requires-Dist: sigr
Requires-Dist: quac
Provides-Extra: dev
Requires-Dist: pandas ; extra == 'dev'
Requires-Dist: numpy >=1.22 ; extra == 'dev'
Requires-Dist: scipy ; extra == 'dev'
Requires-Dist: anndata ; extra == 'dev'
Requires-Dist: scanpy ; extra == 'dev'
Requires-Dist: scrublet ; extra == 'dev'
Requires-Dist: scprep ; extra == 'dev'
Requires-Dist: phate ; extra == 'dev'
Requires-Dist: magic-impute ; extra == 'dev'
Requires-Dist: graphtools ; extra == 'dev'
Requires-Dist: matplotlib ; extra == 'dev'
Requires-Dist: seaborn ; extra == 'dev'
Requires-Dist: excs ; extra == 'dev'
Requires-Dist: torch ; extra == 'dev'
Requires-Dist: scikit-learn ; extra == 'dev'
